plotursheet/__init__.py
plotursheet/__main__.py
plotursheet/command_line.py
plotursheet/plotursheet.py
plotursheet/__pycache__/__init__.cpython-38.pyc
plotursheet/__pycache__/__main__.cpython-38.pyc
plotursheet-1.0.0.dist-info/LICENSE.txt
plotursheet-1.0.0.dist-info/METADATA
plotursheet-1.0.0.dist-info/WHEEL
plotursheet-1.0.0.dist-info/entry_points.txt
plotursheet-1.0.0.dist-info/top_level.txt
plotursheet-1.0.0.dist-info/RECORD
