Metadata-Version: 2.1
Name: plotursheet
Version: 1.0.0
Summary: A small example package
Home-page: https://github.com/fat-a-lity/plotursheet
Author: Varun Chandran
Author-email: varunjay7@gmail.com
License: UNKNOWN
Platform: UNKNOWN
Classifier: Programming Language :: Python :: 3
Classifier: License :: OSI Approved :: MIT License
Classifier: Operating System :: OS Independent
Requires-Python: >=3.6
